pgcron/__init__.py
pgcron/_compat.py
pgcron/_config.py
pgcron/_jobs.py
pgcron/_registry.py
pgcron/_sql.py
pgcron/apps.py
pgcron/checks.py
pgcron/core.py
pgcron/expressions.py
pgcron/models.py
pgcron/py.typed
pgcron/schedule.py
pgcron/management/__init__.py
pgcron/management/commands/__init__.py
pgcron/management/commands/pgcron.py
django_pgcron-0.1.0.dist-info/METADATA
django_pgcron-0.1.0.dist-info/WHEEL
django_pgcron-0.1.0.dist-info/licenses/LICENSE
django_pgcron-0.1.0.dist-info/RECORD
