Metadata-Version: 2.4
Name: django-pgcron
Version: 0.1.0
Summary: Manage pgcron jobs from Django
Author-email: Maxwell Muoto <maxmuoto@gmail.com>
License: MIT License
License-File: LICENSE
Requires-Python: <3.14,>=3.10
Requires-Dist: django>=5.0.0
